business_calendar/__init__.py
business_calendar/business_calendar.py
business_calendar/test/__init__.py
business_calendar/test/speed_comparison.py
business_calendar/test/test_business_calendar.py
business_calendar-0.2.1.dist-info/DESCRIPTION.rst
business_calendar-0.2.1.dist-info/METADATA
business_calendar-0.2.1.dist-info/RECORD
business_calendar-0.2.1.dist-info/WHEEL
business_calendar-0.2.1.dist-info/metadata.json
business_calendar-0.2.1.dist-info/top_level.txt
